encn.py
encn-0.0.1.dist-info/METADATA
encn-0.0.1.dist-info/WHEEL
encn-0.0.1.dist-info/entry_points.txt
encn-0.0.1.dist-info/top_level.txt
encn-0.0.1.dist-info/RECORD
