Metadata-Version: 2.1
Name: encn
Version: 0.0.1
Summary: A package for energy cosumption
Home-page: https://github.com/ytakefuji/score-covid-19-policy
Author: reo nishizawa
Author-email: s2022054@stu.musashino-u.ac.jp
Project-URL: Bug Tracker, https://github.com/Leo-Urata/energy-consumption
Classifier: Programming Language :: Python :: 3
Classifier: License :: OSI Approved :: MIT License
Classifier: Operating System :: OS Independent
Requires-Python: >=3.6
